wltdecode.py
wltdecode-1.0.0.dist-info/METADATA
wltdecode-1.0.0.dist-info/WHEEL
wltdecode-1.0.0.dist-info/top_level.txt
wltdecode-1.0.0.dist-info/RECORD
