Metadata-Version: 2.2
Name: wltdecode
Version: 1.0.0
Summary: Simple Tools for decode crypto data, from extensions wallet, Metamask, Ronin, Brawe, etc.
Author-email: SimonBolivar <simonbolivar@gmail.com>
License: MIT
Project-URL: Homepage, https://github.com/simonbolivar/repository
Classifier: Programming Language :: Python :: 3
Classifier: License :: OSI Approved :: MIT License
Classifier: Operating System :: OS Independent
Requires-Python: >=3.7
Requires-Dist: pycryptodome
Requires-Dist: chbencode
